{
  "name": "Thorin",
  "abilities": {
    "STR": 16,
    "INT": 10,
    "WIS": 11,
    "DEX": 12,
    "CON": 14,
    "CHA": 9
  },
  "race_id": "dwarf",
  "classes": [
    {
      "class_id": "fighter",
      "level": 1,
      "xp": 0,
      "hp_rolls": [
        7
      ]
    }
  ],
  "alignment": "law",
  "secondary_skill": null,
  "weapon_proficiencies": [],
  "weapon_specialisations": [],
  "ruleset": {
    "ascending_ac": false,
    "secondary_skills": false,
    "weapon_proficiency": false,
    "multiclassing": false,
    "reroll_1s_2s_hp_l1": false,
    "separate_race_class": true,
    "variable_weapon_damage": false,
    "encumbrance": "basic"
  },
  "items": []
}